needletail-0.7.0.dist-info/METADATA
needletail-0.7.0.dist-info/WHEEL
needletail-0.7.0.dist-info/licenses/LICENSE
needletail/__init__.py
needletail/__init__.pyi
needletail/py.typed
needletail/needletail.cpython-310-x86_64-linux-gnu.so
needletail-0.7.0.dist-info/RECORD
