Metadata-Version: 2.4
Name: needletail
Version: 0.7.0
License-File: LICENSE
Summary: FASTX parsing and k-mer methods
Keywords: FASTA,FASTQ,kmer,bioinformatics
Author: Roderick Bovee <rbovee@gmail.com>, Vincent Prouillet <vincent@onecodex.com>
Author-email: Roderick Bovee <rbovee@gmail.com>, Vincent Prouillet <vincent@onecodex.com>
License: MIT
Requires-Python: >=3.8
Project-URL: Source Code, https://github.com/onecodex/needletail
